redacted/__init__.py
redacted/__main__.py
redacted/anonymiser.py
redacted/info_types.py
redacted-0.2.1.dist-info/LICENSE
redacted-0.2.1.dist-info/METADATA
redacted-0.2.1.dist-info/WHEEL
redacted-0.2.1.dist-info/top_level.txt
redacted-0.2.1.dist-info/RECORD
